pgbar/__init__.py
pgbar/pgbar.py
pgbar/pgcounter.py
pgbar/pgspinner.py
pgbar-0.3.dist-info/LICENSE
pgbar-0.3.dist-info/METADATA
pgbar-0.3.dist-info/WHEEL
pgbar-0.3.dist-info/top_level.txt
pgbar-0.3.dist-info/RECORD
