Metadata-Version: 2.1
Name: pgbar
Version: 0.3
Summary: Terminal Progress Bar
Home-page: https://gitlab.com/sajeeshen/python-terminal-progress
Author: Sajeesh E Namboothiri
Author-email: sajeeshe@gmail.com
License: UNKNOWN
Platform: UNKNOWN
Classifier: Programming Language :: Python :: 3
Classifier: License :: OSI Approved :: MIT License
Classifier: Operating System :: OS Independent
